Metadata-Version: 1.0
Name: ncp
Version: 1.15
Summary: nginx 配置文件生成工具
Home-page: UNKNOWN
Author: liu rui
Author-email: 1313475@qq.com
License: http://www.apache.org/licenses/LICENSE-2.0
Platform: UNKNOWN
